LICENSE
MANIFEST.in
README.md
setup.py
cocotb_test/Makefile.inc
cocotb_test/__init__.py
cocotb_test/cli.py
cocotb_test/plugin.py
cocotb_test/run.py
cocotb_test/simulator.py
cocotb_test.egg-info/PKG-INFO
cocotb_test.egg-info/SOURCES.txt
cocotb_test.egg-info/dependency_links.txt
cocotb_test.egg-info/entry_points.txt
cocotb_test.egg-info/requires.txt
cocotb_test.egg-info/top_level.txt
tests/test_cocotb_examples.py
tests/test_cocotb_tests.py
tests/test_compile_errors.py
tests/test_dff.py
tests/test_dff_custom_sim.py
tests/test_long_log.py
tests/test_multitop.py
tests/test_named_lib.py
tests/test_parallel.py
tests/test_parameters.py
tests/test_plus_args.py
tests/test_simulator_kwarg.py