Metadata-Version: 2.1
Name: cocotb-test
Version: 0.2.5
Home-page: 
Author: Tomasz Hemperek
Author-email: hemperek@uni-bonn.de
License: BSD
Platform: any
Classifier: Programming Language :: Python :: 3
Classifier: License :: OSI Approved :: BSD License
Classifier: Topic :: Scientific/Engineering :: Electronic Design Automation (EDA)
Classifier: Framework :: cocotb
Requires-Python: >=3.7
License-File: LICENSE
Requires-Dist: cocotb>=1.5
Requires-Dist: pytest
Requires-Dist: find_libpython
